allskycam/__init__.py
allskycam/__main__.py
allskycam/allskycamdelete.py
allskycam/config.txt
allskycam/fileManager.py
allskycam/imageHeader.py
allskycam/suncalc2.py
allskycam/test.py
allskycam/timelapse.py
allskycam/watchDog.py
frank_AllSkyCamPi-1.26.0.dist-info/METADATA
frank_AllSkyCamPi-1.26.0.dist-info/WHEEL
frank_AllSkyCamPi-1.26.0.dist-info/entry_points.txt
frank_AllSkyCamPi-1.26.0.dist-info/top_level.txt
frank_AllSkyCamPi-1.26.0.dist-info/RECORD
