Metadata-Version: 2.1
Name: frank-AllSkyCamPi
Version: 1.26.0
Summary: UNKNOWN
Home-page: https://github.com/sferlix/frank-AllSkyCamPi
Author: Francesco Sferlazza
Author-email: sferlazza@gmail.com
License: MIT
Platform: UNKNOWN
Classifier: License :: OSI Approved :: MIT License
Classifier: Programming Language :: Python :: 3
Classifier: Programming Language :: Python :: 3.7
Requires-Dist: pytz
